Metadata-Version: 2.4
Name: terraback
Version: 0.5.0
Summary: Terraback: Universal infrastructure scanning and Terraform generation tool
Home-page: https://terraback.io
Author: Terraback Team
Author-email: support@terraback.io
Classifier: Development Status :: 4 - Beta
Classifier: Intended Audience :: Developers
Classifier: Intended Audience :: System Administrators
Classifier: Topic :: System :: Systems Administration
Classifier: Topic :: Software Development :: Code Generators
Classifier: License :: Other/Proprietary License
Classifier: Programming Language :: Python :: 3
Classifier: Programming Language :: Python :: 3.8
Classifier: Programming Language :: Python :: 3.9
Classifier: Programming Language :: Python :: 3.10
Classifier: Programming Language :: Python :: 3.11
Classifier: Operating System :: OS Independent
Requires-Python: >=3.8
License-File: LICENSE
Requires-Dist: boto3==1.38.21
Requires-Dist: botocore==1.38.21
Requires-Dist: azure-identity==1.15.0
Requires-Dist: azure-mgmt-resource==23.1.0
Requires-Dist: azure-mgmt-compute==31.0.0
Requires-Dist: azure-mgmt-network==27.0.0
Requires-Dist: azure-mgmt-storage==21.2.0
Requires-Dist: azure-mgmt-web==7.3.0
Requires-Dist: azure-mgmt-sql==3.0.1
Requires-Dist: azure-mgmt-keyvault==10.3.0
Requires-Dist: azure-mgmt-monitor==6.0.0
Requires-Dist: azure-mgmt-redis==14.3.0
Requires-Dist: azure-mgmt-cdn==13.1.0
Requires-Dist: azure-mgmt-dns==8.1.0
Requires-Dist: azure-mgmt-servicebus==8.2.0
Requires-Dist: azure-mgmt-eventhub==11.0.0
Requires-Dist: azure-mgmt-loganalytics==13.0.0b6
Requires-Dist: azure-mgmt-apimanagement==4.0.0
Requires-Dist: azure-mgmt-msi==7.0.0
Requires-Dist: azure-mgmt-authorization==4.0.0
Requires-Dist: azure-mgmt-containerregistry==10.3.0
Requires-Dist: azure-mgmt-containerservice==30.0.0
Requires-Dist: azure-core==1.30.0
Requires-Dist: azure-keyvault-secrets==4.7.0
Requires-Dist: azure-keyvault-keys==4.8.0
Requires-Dist: azure-keyvault-certificates==4.7.0
Requires-Dist: google-cloud-compute==1.14.0
Requires-Dist: google-cloud-storage==2.10.0
Requires-Dist: google-cloud-resource-manager==1.10.0
Requires-Dist: google-auth==2.23.0
Requires-Dist: google-cloud-pubsub==2.18.1
Requires-Dist: google-cloud-secret-manager==2.16.4
Requires-Dist: cloud-sql-python-connector>=1.4.0
Requires-Dist: google-api-python-client==2.103.0
Requires-Dist: google-cloud-container==2.28.0
Requires-Dist: google-cloud-iam==2.12.1
Requires-Dist: google-cloud-monitoring==2.15.1
Requires-Dist: google-cloud-dns==0.34.1
Requires-Dist: google-cloud-run==0.10.0
Requires-Dist: typer[all]==0.15.4
Requires-Dist: click==8.1.8
Requires-Dist: rich==14.0.0
Requires-Dist: colorama==0.4.6
Requires-Dist: Pygments==2.19.1
Requires-Dist: Jinja2==3.1.6
Requires-Dist: MarkupSafe==3.0.2
Requires-Dist: requests
Requires-Dist: cryptography
Requires-Dist: paramiko
Requires-Dist: pyyaml
Requires-Dist: jmespath==1.0.1
Requires-Dist: markdown-it-py==3.0.0
Requires-Dist: mdurl==0.1.2
Requires-Dist: python-dateutil==2.9.0.post0
Requires-Dist: shellingham==1.5.4
Requires-Dist: six==1.17.0
Requires-Dist: typing_extensions>=4.0.0
Requires-Dist: urllib3<2.0,>=1.26.0
Dynamic: author
Dynamic: author-email
Dynamic: classifier
Dynamic: description
Dynamic: description-content-type
Dynamic: home-page
Dynamic: license-file
Dynamic: requires-dist
Dynamic: requires-python
Dynamic: summary
